LICENSE
README.md
setup.py
dcca/__init__.py
dcca/cross_correlation.py
dcca.egg-info/PKG-INFO
dcca.egg-info/SOURCES.txt
dcca.egg-info/dependency_links.txt
dcca.egg-info/requires.txt
dcca.egg-info/top_level.txt