Metadata-Version: 2.1
Name: dcca
Version: 0.3.0
Summary: Python implementation of the Time-Lagged Detrended Cross-Correlation Coefficient Analysis (DCCA)
Home-page: https://github.com/LeonardoAlchieri/dcca
Author: Leonardo Alchieri
Author-email: leonardo@alchieri.eu
License: GPLv3
Classifier: Development Status :: 3 - Alpha
Classifier: Intended Audience :: Science/Research
Classifier: License :: OSI Approved :: BSD License
Classifier: Operating System :: POSIX :: Linux
Classifier: Programming Language :: Python :: 3.7
Classifier: Programming Language :: Python :: 3.8
Classifier: Programming Language :: Python :: 3.9
Classifier: Programming Language :: Python :: 3.10
Classifier: Programming Language :: Python :: 3.11
Requires-Python: >=3.6
License-File: LICENSE
